pywebcore/__init__.py
pywebcore/pywebcore.py
pywebcore-0.0.4.dist-info/LICENSE
pywebcore-0.0.4.dist-info/METADATA
pywebcore-0.0.4.dist-info/WHEEL
pywebcore-0.0.4.dist-info/top_level.txt
pywebcore-0.0.4.dist-info/RECORD
